dagster_serde/__init__.py
dagster_serde/_version.py
dagster_serde/py.typed
dagster_serde/utils.py
dagster_serde/io_managers/__init__.py
dagster_serde/io_managers/base.py
dagster_serde/io_managers/json.py
dagster_serde/io_managers/yaml.py
dagster_serde-0.0.3.dist-info/METADATA
dagster_serde-0.0.3.dist-info/WHEEL
dagster_serde-0.0.3.dist-info/licenses/LICENSE
dagster_serde-0.0.3.dist-info/RECORD
